LICENSE
README.rst
setup.py
testflows.github.runners.egg-info/PKG-INFO
testflows.github.runners.egg-info/SOURCES.txt
testflows.github.runners.egg-info/dependency_links.txt
testflows.github.runners.egg-info/not-zip-safe
testflows.github.runners.egg-info/requires.txt
testflows.github.runners.egg-info/top_level.txt
testflows/github/runners/__init__.py
testflows/github/runners/actions.py
testflows/github/runners/api_watch.py
testflows/github/runners/args.py
testflows/github/runners/cloud.py
testflows/github/runners/delete.py
testflows/github/runners/logger.py
testflows/github/runners/request.py
testflows/github/runners/scale_down.py
testflows/github/runners/scale_up.py
testflows/github/runners/server.py
testflows/github/runners/servers.py
testflows/github/runners/service.py
testflows/github/runners/shell.py
testflows/github/runners/bin/github-runners
testflows/github/runners/config/__init__.py
testflows/github/runners/config/config.py
testflows/github/runners/config/schema.json
testflows/github/runners/scripts/__init__.py
testflows/github/runners/scripts/setup.sh
testflows/github/runners/scripts/setup_docker.sh
testflows/github/runners/scripts/startup_arm64.sh
testflows/github/runners/scripts/startup_x64.sh
testflows/github/runners/scripts/deploy/__init__.py
testflows/github/runners/scripts/deploy/setup.sh