Metadata-Version: 2.1
Name: testflows.github.runners
Version: 1.5.230805.1021151
Summary: Autoscaling GitHub Actions Runners Using Hetzner Cloud 
Home-page: https://github.com/testflows/github-runners
Author: Vitaliy Zakaznikov
Author-email: vzakaznikov@testflows.com
License: Apache-2.0
Classifier: Development Status :: 4 - Beta
Classifier: Programming Language :: Python :: 3
Classifier: License :: OSI Approved :: Apache Software License
Classifier: Operating System :: POSIX :: Linux
Requires-Python: >=3.8
Provides-Extra: dev
License-File: LICENSE
